ondemand/__init__.py
ondemand/ondemand_client.py
ondemand-1.1.1.dist-info/LICENSE.txt
ondemand-1.1.1.dist-info/METADATA
ondemand-1.1.1.dist-info/WHEEL
ondemand-1.1.1.dist-info/top_level.txt
ondemand-1.1.1.dist-info/RECORD
